README.md
setup.py
pDiffusionMap/DataSource.py
pDiffusionMap/Graph.py
pDiffusionMap/__init__.py
pDiffusionMap/abbr.py
pDiffusionMap/util.py
pDiffusionMap/visutil.py
pDiffusionMap.egg-info/PKG-INFO
pDiffusionMap.egg-info/SOURCES.txt
pDiffusionMap.egg-info/dependency_links.txt
pDiffusionMap.egg-info/top_level.txt