Metadata-Version: 1.2
Name: pDiffusionMap
Version: 0.2.4
Summary: This package aims to do Diffusion Map in a parallel way. 
Home-page: https://github.com/haoyuanli93/DiffusionMap
Author: Haoyuan Li
Author-email: hyli16@stanford.edu
Maintainer: Haoyuan Li
Maintainer-email: hyli16@stanford.edu
License: BSD License
Platform: Linux
